privacera_securechat/.coverage
privacera_securechat/.coveragerc
privacera_securechat/__init__.py
privacera_securechat/__main__.py
privacera_securechat/_version.py
privacera_securechat/launcher.py
privacera_securechat/run_db_setup.sh
privacera_securechat/run_gunicorn.sh
privacera_securechat/run_unit_test.sh
privacera_securechat/app/__init__.py
privacera_securechat/app/server.py
privacera_securechat/app/thread_server.py
privacera_securechat/app/api_schemas/__init__.py
privacera_securechat/app/api_schemas/conversations.py
privacera_securechat/app/api_schemas/error_response.py
privacera_securechat/app/api_schemas/user.py
privacera_securechat/app/controllers/AI_applications.py
privacera_securechat/app/controllers/__init__.py
privacera_securechat/app/controllers/conversation.py
privacera_securechat/app/controllers/health_check.py
privacera_securechat/app/controllers/user.py
privacera_securechat/app/db_models/__init__.py
privacera_securechat/app/db_models/conversation_model.py
privacera_securechat/app/db_models/message_model.py
privacera_securechat/app/db_models/user_model.py
privacera_securechat/app/db_operations/__init__.py
privacera_securechat/app/db_operations/conversation_repository.py
privacera_securechat/app/db_operations/message_repository.py
privacera_securechat/app/db_operations/user_repository.py
privacera_securechat/configs/AI_applications.json
privacera_securechat/configs/default_config.yaml
privacera_securechat/configs/logging.ini
privacera_securechat/configs/standalone_config.yaml
privacera_securechat/configs/test_config.yaml
privacera_securechat/configs/user_secrets.csv
privacera_securechat/core/__init__.py
privacera_securechat/core/config.py
privacera_securechat/core/constants.py
privacera_securechat/core/llm_constants.py
privacera_securechat/core/logging_init.py
privacera_securechat/core/utils.py
privacera_securechat/core/database/__init__.py
privacera_securechat/core/database/session.py
privacera_securechat/core/database/transactional.py
privacera_securechat-1.0.4.dist-info/METADATA
privacera_securechat-1.0.4.dist-info/WHEEL
privacera_securechat-1.0.4.dist-info/entry_points.txt
privacera_securechat-1.0.4.dist-info/licenses/LICENSE
privacera_securechat-1.0.4.dist-info/RECORD
