Metadata-Version: 2.3
Name: privacera_securechat
Version: 1.0.4
Summary: Privacera Secure Chat is a conversational AI chatbot
Project-URL: Homepage, https://github.com/pypa/privacera_securechat
Project-URL: Bug Tracker, https://github.com/pypa/privacera_securechat/issues
Author-email: Privacera  <support@privacera.com>
License:                                  Apache License
License-File: LICENSE
Keywords: Chatbot,Governance,PAIG,Privacy,Security
Classifier: License :: Other/Proprietary License
Classifier: Operating System :: OS Independent
Classifier: Programming Language :: Python :: 3
Requires-Python: >=3.9
Requires-Dist: aiosqlite
Requires-Dist: alembic
Requires-Dist: boto3>=1.28.57
Requires-Dist: chromadb
Requires-Dist: click
Requires-Dist: fastapi
Requires-Dist: greenlet
Requires-Dist: jinja2
Requires-Dist: langchain-community==0.2.0
Requires-Dist: langchain-openai==0.1.7
Requires-Dist: langchain==0.2.0
Requires-Dist: okta-jwt-verifier
Requires-Dist: openai
Requires-Dist: opensearch-py
Requires-Dist: paig-client
Requires-Dist: pandas
Requires-Dist: pydantic
Requires-Dist: pydantic-settings
Requires-Dist: python-jose
Requires-Dist: sqlalchemy
Requires-Dist: tiktoken
Requires-Dist: urllib3
Requires-Dist: uvicorn
Requires-Dist: werkzeug
Provides-Extra: bedrock
Requires-Dist: boto3>=1.28.57; extra == 'bedrock'
Provides-Extra: chromadb
Requires-Dist: chroma-hnswlib; extra == 'chromadb'
Requires-Dist: chromadb; extra == 'chromadb'
Provides-Extra: dev
Requires-Dist: pytest; extra == 'dev'
Requires-Dist: pytest-asyncio; extra == 'dev'
Requires-Dist: pytest-cov; extra == 'dev'
Requires-Dist: pytest-mock; extra == 'dev'
Requires-Dist: uvicorn[standard]; extra == 'dev'
Provides-Extra: google-colab
Requires-Dist: nest-asyncio; extra == 'google-colab'
Provides-Extra: milvus
Requires-Dist: pymilvus; extra == 'milvus'
Provides-Extra: opensearch
Requires-Dist: boto3>=1.28.57; extra == 'opensearch'
Requires-Dist: opensearch-py; extra == 'opensearch'
